{
  "CF258425819": {
    "contest_id": 1966,
    "language": "C++17 (GCC 7-32)",
    "path": "codeforces/1966/B.cpp",
    "platform": "Codeforces",
    "problem_index": "B",
    "problem_name": "Rectangle Filling",
    "problem_url": "https://codeforces.com/contest/1966/problem/B",
    "submission_id": "CF258425819",
    "submission_url": "https://codeforces.com/contest/1966/submission/258425819",
    "tags": [
      "constructive algorithms",
      "implementation",
      "*1100"
    ],
    "timestamp": "Apr/27/2024 15:50"
  },
  "CF258437592": {
    "contest_id": 1966,
    "language": "C++17 (GCC 7-32)",
    "path": "codeforces/1966/C.cpp",
    "platform": "Codeforces",
    "problem_index": "C",
    "problem_name": "Everything Nim",
    "problem_url": "https://codeforces.com/contest/1966/problem/C",
    "submission_id": "CF258437592",
    "submission_url": "https://codeforces.com/contest/1966/submission/258437592",
    "tags": [
      "games",
      "greedy",
      "*1400"
    ],
    "timestamp": "Apr/27/2024 16:13"
  },
  "CF258449170": {
    "contest_id": 1966,
    "language": "C++17 (GCC 7-32)",
    "path": "codeforces/1966/D.cpp",
    "platform": "Codeforces",
    "problem_index": "D",
    "problem_name": "Missing Subsequence Sum",
    "problem_url": "https://codeforces.com/contest/1966/problem/D",
    "submission_id": "CF258449170",
    "submission_url": "https://codeforces.com/contest/1966/submission/258449170",
    "tags": [
      "constructive algorithms",
      "greedy",
      "math",
      "number theory",
      "*1800"
    ],
    "timestamp": "Apr/27/2024 16:41"
  },
  "CF258866546": {
    "contest_id": 1972,
    "language": "C++17 (GCC 7-32)",
    "path": "codeforces/1972/A.cpp",
    "platform": "Codeforces",
    "problem_index": "A",
    "problem_name": "Contest Proposal",
    "problem_url": "https://codeforces.com/contest/1972/problem/A",
    "submission_id": "CF258866546",
    "submission_url": "https://codeforces.com/contest/1972/submission/258866546",
    "tags": [
      "brute force",
      "greedy",
      "two pointers",
      "*800"
    ],
    "timestamp": "Apr/30/2024 15:40"
  },
  "CF258884684": {
    "contest_id": 1972,
    "language": "C++17 (GCC 7-32)",
    "path": "codeforces/1972/B.cpp",
    "platform": "Codeforces",
    "problem_index": "B",
    "problem_name": "Coin Games",
    "problem_url": "https://codeforces.com/contest/1972/problem/B",
    "submission_id": "CF258884684",
    "submission_url": "https://codeforces.com/contest/1972/submission/258884684",
    "tags": [
      "games",
      "*900"
    ],
    "timestamp": "Apr/30/2024 16:07"
  },
  "CF258895291": {
    "contest_id": 1972,
    "language": "C++17 (GCC 7-32)",
    "path": "codeforces/1972/C.cpp",
    "platform": "Codeforces",
    "problem_index": "C",
    "problem_name": "Permutation Counting",
    "problem_url": "https://codeforces.com/contest/1972/problem/C",
    "submission_id": "CF258895291",
    "submission_url": "https://codeforces.com/contest/1972/submission/258895291",
    "tags": [
      "binary search",
      "constructive algorithms",
      "greedy",
      "implementation",
      "math",
      "sortings",
      "*1400"
    ],
    "timestamp": "Apr/30/2024 16:31"
  },
  "CF258906795": {
    "contest_id": 1972,
    "language": "C++17 (GCC 7-32)",
    "path": "codeforces/1972/D1.cpp",
    "platform": "Codeforces",
    "problem_index": "D1",
    "problem_name": "Reverse Card (Easy Version)",
    "problem_url": "https://codeforces.com/contest/1972/problem/D1",
    "submission_id": "CF258906795",
    "submission_url": "https://codeforces.com/contest/1972/submission/258906795",
    "tags": [
      "brute force",
      "math",
      "number theory",
      "*1400"
    ],
    "timestamp": "Apr/30/2024 17:06"
  },
  "CF258991205": {
    "contest_id": 1972,
    "language": "C++17 (GCC 7-32)",
    "path": "codeforces/1972/D2.cpp",
    "platform": "Codeforces",
    "problem_index": "D2",
    "problem_name": "Reverse Card (Hard Version)",
    "problem_url": "https://codeforces.com/contest/1972/problem/D2",
    "submission_id": "CF258991205",
    "submission_url": "https://codeforces.com/contest/1972/submission/258991205",
    "tags": [
      "brute force",
      "math",
      "number theory",
      "*2200"
    ],
    "timestamp": "May/01/2024 10:42"
  },
  "CF258991606": {
    "contest_id": 1972,
    "language": "C++17 (GCC 7-32)",
    "path": "codeforces/1972/C.cpp",
    "platform": "Codeforces",
    "problem_index": "C",
    "problem_name": "Permutation Counting",
    "problem_url": "https://codeforces.com/contest/1972/problem/C",
    "submission_id": "CF258991606",
    "submission_url": "https://codeforces.com/contest/1972/submission/258991606",
    "tags": [
      "binary search",
      "constructive algorithms",
      "greedy",
      "implementation",
      "math",
      "sortings",
      "*1400"
    ],
    "timestamp": "May/01/2024 10:47"
  },
  "CF259120718": {
    "contest_id": 1649,
    "language": "C++17 (GCC 7-32)",
    "path": "codeforces/1649/A.cpp",
    "platform": "Codeforces",
    "problem_index": "A",
    "problem_name": "Game",
    "problem_url": "https://codeforces.com/contest/1649/problem/A",
    "submission_id": "CF259120718",
    "submission_url": "https://codeforces.com/contest/1649/submission/259120718",
    "tags": [
      "implementation",
      "*800"
    ],
    "timestamp": "May/02/2024 13:37"
  },
  "CF259246579": {
    "contest_id": 1649,
    "language": "C++17 (GCC 7-32)",
    "path": "codeforces/1649/B.cpp",
    "platform": "Codeforces",
    "problem_index": "B",
    "problem_name": "Game of Ball Passing",
    "problem_url": "https://codeforces.com/contest/1649/problem/B",
    "submission_id": "CF259246579",
    "submission_url": "https://codeforces.com/contest/1649/submission/259246579",
    "tags": [
      "greedy",
      "implementation",
      "*1300"
    ],
    "timestamp": "May/02/2024 17:59"
  },
  "CF259464025": {
    "contest_id": 1970,
    "language": "C++17 (GCC 7-32)",
    "path": "codeforces/1970/A1.cpp",
    "platform": "Codeforces",
    "problem_index": "A1",
    "problem_name": "Balanced Shuffle (Easy)",
    "problem_url": "https://codeforces.com/contest/1970/problem/A1",
    "submission_id": "CF259464025",
    "submission_url": "https://codeforces.com/contest/1970/submission/259464025",
    "tags": [
      "implementation",
      "sortings",
      "*1000"
    ],
    "timestamp": "May/04/2024 08:10"
  },
  "CF259466122": {
    "contest_id": 1970,
    "language": "C++17 (GCC 7-32)",
    "path": "codeforces/1970/C1.cpp",
    "platform": "Codeforces",
    "problem_index": "C1",
    "problem_name": "Game on Tree (Easy)",
    "problem_url": "https://codeforces.com/contest/1970/problem/C1",
    "submission_id": "CF259466122",
    "submission_url": "https://codeforces.com/contest/1970/submission/259466122",
    "tags": [
      "games",
      "*1400"
    ],
    "timestamp": "May/04/2024 08:23"
  },
  "CF259472136": {
    "contest_id": 1970,
    "language": "C++17 (GCC 7-32)",
    "path": "codeforces/1970/C2.cpp",
    "platform": "Codeforces",
    "problem_index": "C2",
    "problem_name": "Game on Tree (Medium)",
    "problem_url": "https://codeforces.com/contest/1970/problem/C2",
    "submission_id": "CF259472136",
    "submission_url": "https://codeforces.com/contest/1970/submission/259472136",
    "tags": [
      "dfs and similar",
      "dp",
      "games",
      "trees",
      "*1700"
    ],
    "timestamp": "May/04/2024 09:00"
  },
  "CF259472167": {
    "contest_id": 1970,
    "language": "C++17 (GCC 7-32)",
    "path": "codeforces/1970/C3.cpp",
    "platform": "Codeforces",
    "problem_index": "C3",
    "problem_name": "Game on Tree (Hard)",
    "problem_url": "https://codeforces.com/contest/1970/problem/C3",
    "submission_id": "CF259472167",
    "submission_url": "https://codeforces.com/contest/1970/submission/259472167",
    "tags": [
      "dfs and similar",
      "dp",
      "games",
      "trees",
      "*1900"
    ],
    "timestamp": "May/04/2024 09:00"
  },
  "CF259473093": {
    "contest_id": 1970,
    "language": "C++17 (GCC 7-32)",
    "path": "codeforces/1970/G1.cpp",
    "platform": "Codeforces",
    "problem_index": "G1",
    "problem_name": "Min-Fund Prison (Easy)",
    "problem_url": "https://codeforces.com/contest/1970/problem/G1",
    "submission_id": "CF259473093",
    "submission_url": "https://codeforces.com/contest/1970/submission/259473093",
    "tags": [
      "dfs and similar",
      "trees",
      "*1900"
    ],
    "timestamp": "May/04/2024 09:06"
  },
  "CF259474437": {
    "contest_id": 1970,
    "language": "C++17 (GCC 7-32)",
    "path": "codeforces/1970/E1.cpp",
    "platform": "Codeforces",
    "problem_index": "E1",
    "problem_name": "Trails (Easy)",
    "problem_url": "https://codeforces.com/contest/1970/problem/E1",
    "submission_id": "CF259474437",
    "submission_url": "https://codeforces.com/contest/1970/submission/259474437",
    "tags": [
      "dp",
      "*1800"
    ],
    "timestamp": "May/04/2024 09:15"
  },
  "CF259476644": {
    "contest_id": 1970,
    "language": "C++17 (GCC 7-32)",
    "path": "codeforces/1970/E2.cpp",
    "platform": "Codeforces",
    "problem_index": "E2",
    "problem_name": "Trails (Medium)",
    "problem_url": "https://codeforces.com/contest/1970/problem/E2",
    "submission_id": "CF259476644",
    "submission_url": "https://codeforces.com/contest/1970/submission/259476644",
    "tags": [
      "dp",
      "matrices",
      "*2000"
    ],
    "timestamp": "May/04/2024 09:30"
  },
  "CF259485925": {
    "contest_id": 1970,
    "language": "C++17 (GCC 7-32)",
    "path": "codeforces/1970/B1.cpp",
    "platform": "Codeforces",
    "problem_index": "B1",
    "problem_name": "Exact Neighbours (Easy)",
    "problem_url": "https://codeforces.com/contest/1970/problem/B1",
    "submission_id": "CF259485925",
    "submission_url": "https://codeforces.com/contest/1970/submission/259485925",
    "tags": [
      "constructive algorithms",
      "*1900"
    ],
    "timestamp": "May/04/2024 10:35"
  },
  "CF259487533": {
    "contest_id": 1970,
    "language": "C++17 (GCC 7-32)",
    "path": "codeforces/1970/B2.cpp",
    "platform": "Codeforces",
    "problem_index": "B2",
    "problem_name": "Exact Neighbours (Medium)",
    "problem_url": "https://codeforces.com/contest/1970/problem/B2",
    "submission_id": "CF259487533",
    "submission_url": "https://codeforces.com/contest/1970/submission/259487533",
    "tags": [
      "constructive algorithms",
      "*2100"
    ],
    "timestamp": "May/04/2024 10:46"
  },
  "CF259490004": {
    "contest_id": 1970,
    "language": "C++17 (GCC 7-32)",
    "path": "codeforces/1970/G2.cpp",
    "platform": "Codeforces",
    "problem_index": "G2",
    "problem_name": "Min-Fund Prison (Medium)",
    "problem_url": "https://codeforces.com/contest/1970/problem/G2",
    "submission_id": "CF259490004",
    "submission_url": "https://codeforces.com/contest/1970/submission/259490004",
    "tags": [
      "brute force",
      "dfs and similar",
      "dp",
      "graphs",
      "trees",
      "*2200"
    ],
    "timestamp": "May/04/2024 11:05"
  },
  "CF259498696": {
    "contest_id": 1970,
    "language": "C++17 (GCC 7-32)",
    "path": "codeforces/1970/D1.cpp",
    "platform": "Codeforces",
    "problem_index": "D1",
    "problem_name": "Arithmancy (Easy)",
    "problem_url": "https://codeforces.com/contest/1970/problem/D1",
    "submission_id": "CF259498696",
    "submission_url": "https://codeforces.com/contest/1970/submission/259498696",
    "tags": [
      "brute force",
      "constructive algorithms",
      "interactive",
      "strings",
      "*2100"
    ],
    "timestamp": "May/04/2024 12:14"
  },
  "CF259500643": {
    "contest_id": 1970,
    "language": "C++17 (GCC 7-32)",
    "path": "codeforces/1970/F1.cpp",
    "platform": "Codeforces",
    "problem_index": "F1",
    "problem_name": "Playing Quidditch (Easy)",
    "problem_url": "https://codeforces.com/contest/1970/problem/F1",
    "submission_id": "CF259500643",
    "submission_url": "https://codeforces.com/contest/1970/submission/259500643",
    "tags": [
      "implementation",
      "*2300"
    ],
    "timestamp": "May/04/2024 12:30"
  },
  "CF259738231": {
    "contest_id": 1674,
    "language": "C++17 (GCC 7-32)",
    "path": "codeforces/1674/F.cpp",
    "platform": "Codeforces",
    "problem_index": "F",
    "problem_name": "Desktop Rearrangement",
    "problem_url": "https://codeforces.com/contest/1674/problem/F",
    "submission_id": "CF259738231",
    "submission_url": "https://codeforces.com/contest/1674/submission/259738231",
    "tags": [
      "data structures",
      "greedy",
      "implementation",
      "*1800"
    ],
    "timestamp": "May/06/2024 12:07"
  },
  "CF259745004": {
    "contest_id": 1714,
    "language": "C++17 (GCC 7-32)",
    "path": "codeforces/1714/F.cpp",
    "platform": "Codeforces",
    "problem_index": "F",
    "problem_name": "Build a Tree and That Is It",
    "problem_url": "https://codeforces.com/contest/1714/problem/F",
    "submission_id": "CF259745004",
    "submission_url": "https://codeforces.com/contest/1714/submission/259745004",
    "tags": [
      "constructive algorithms",
      "implementation",
      "trees",
      "*1900"
    ],
    "timestamp": "May/06/2024 13:03"
  },
  "CF261353296": {
    "contest_id": 1973,
    "language": "C++17 (GCC 7-32)",
    "path": "codeforces/1973/A.cpp",
    "platform": "Codeforces",
    "problem_index": "A",
    "problem_name": "Chess For Three",
    "problem_url": "https://codeforces.com/contest/1973/problem/A",
    "submission_id": "CF261353296",
    "submission_url": "https://codeforces.com/contest/1973/submission/261353296",
    "tags": [
      "brute force",
      "dp",
      "implementation",
      "math",
      "*900"
    ],
    "timestamp": "May/17/2024 15:50"
  },
  "CF261368070": {
    "contest_id": 1973,
    "language": "C++17 (GCC 7-32)",
    "path": "codeforces/1973/B.cpp",
    "platform": "Codeforces",
    "problem_index": "B",
    "problem_name": "Cat, Fox and the Lonely Array",
    "problem_url": "https://codeforces.com/contest/1973/problem/B",
    "submission_id": "CF261368070",
    "submission_url": "https://codeforces.com/contest/1973/submission/261368070",
    "tags": [
      "binary search",
      "bitmasks",
      "data structures",
      "greedy",
      "math",
      "two pointers",
      "*1300"
    ],
    "timestamp": "May/17/2024 16:11"
  },
  "CF261411542": {
    "contest_id": 1973,
    "language": "C++17 (GCC 7-32)",
    "path": "codeforces/1973/C.cpp",
    "platform": "Codeforces",
    "problem_index": "C",
    "problem_name": "Cat, Fox and Double Maximum",
    "problem_url": "https://codeforces.com/contest/1973/problem/C",
    "submission_id": "CF261411542",
    "submission_url": "https://codeforces.com/contest/1973/submission/261411542",
    "tags": [
      "constructive algorithms",
      "greedy",
      "implementation",
      "math",
      "sortings",
      "*1700"
    ],
    "timestamp": "May/17/2024 18:03"
  },
  "CF262522082": {
    "contest_id": 1975,
    "language": "C++17 (GCC 7-32)",
    "path": "codeforces/1975/A.cpp",
    "platform": "Codeforces",
    "problem_index": "A",
    "problem_name": "Bazoka and Mocha's Array",
    "problem_url": "https://codeforces.com/contest/1975/problem/A",
    "submission_id": "CF262522082",
    "submission_url": "https://codeforces.com/contest/1975/submission/262522082",
    "tags": [
      "brute force",
      "greedy",
      "implementation",
      "sortings",
      "*800"
    ],
    "timestamp": "May/25/2024 15:38"
  },
  "CF262526356": {
    "contest_id": 1975,
    "language": "C++17 (GCC 7-32)",
    "path": "codeforces/1975/B.cpp",
    "platform": "Codeforces",
    "problem_index": "B",
    "problem_name": "378QAQ and Mocha's Array",
    "problem_url": "https://codeforces.com/contest/1975/problem/B",
    "submission_id": "CF262526356",
    "submission_url": "https://codeforces.com/contest/1975/submission/262526356",
    "tags": [
      "brute force",
      "greedy",
      "math",
      "sortings",
      "*1000"
    ],
    "timestamp": "May/25/2024 15:43"
  },
  "CF262565314": {
    "contest_id": 1975,
    "language": "C++17 (GCC 7-32)",
    "path": "codeforces/1975/C.cpp",
    "platform": "Codeforces",
    "problem_index": "C",
    "problem_name": "Chamo and Mocha's Array",
    "problem_url": "https://codeforces.com/contest/1975/problem/C",
    "submission_id": "CF262565314",
    "submission_url": "https://codeforces.com/contest/1975/submission/262565314",
    "tags": [
      "binary search",
      "brute force",
      "greedy",
      "*1200"
    ],
    "timestamp": "May/25/2024 16:25"
  },
  "CF262682496": {
    "contest_id": 1975,
    "language": "C++17 (GCC 7-32)",
    "path": "codeforces/1975/D.cpp",
    "platform": "Codeforces",
    "problem_index": "D",
    "problem_name": "Paint the Tree",
    "problem_url": "https://codeforces.com/contest/1975/problem/D",
    "submission_id": "CF262682496",
    "submission_url": "https://codeforces.com/contest/1975/submission/262682496",
    "tags": [
      "brute force",
      "dfs and similar",
      "dp",
      "greedy",
      "shortest paths",
      "trees",
      "*1700"
    ],
    "timestamp": "May/26/2024 10:36"
  },
  "CF263272477": {
    "contest_id": 1976,
    "language": "C++17 (GCC 7-32)",
    "path": "codeforces/1976/A.cpp",
    "platform": "Codeforces",
    "problem_index": "A",
    "problem_name": "Verify Password",
    "problem_url": "https://codeforces.com/contest/1976/problem/A",
    "submission_id": "CF263272477",
    "submission_url": "https://codeforces.com/contest/1976/submission/263272477",
    "tags": [
      "implementation",
      "sortings",
      "strings",
      "*800"
    ],
    "timestamp": "May/30/2024 15:40"
  },
  "CF263292619": {
    "contest_id": 1976,
    "language": "C++17 (GCC 7-32)",
    "path": "codeforces/1976/B.cpp",
    "platform": "Codeforces",
    "problem_index": "B",
    "problem_name": "Increase/Decrease/Copy",
    "problem_url": "https://codeforces.com/contest/1976/problem/B",
    "submission_id": "CF263292619",
    "submission_url": "https://codeforces.com/contest/1976/submission/263292619",
    "tags": [
      "greedy",
      "implementation",
      "*1100"
    ],
    "timestamp": "May/30/2024 15:56"
  },
  "CF263337932": {
    "contest_id": 1976,
    "language": "C++17 (GCC 7-32)",
    "path": "codeforces/1976/C.cpp",
    "platform": "Codeforces",
    "problem_index": "C",
    "problem_name": "Job Interview",
    "problem_url": "https://codeforces.com/contest/1976/problem/C",
    "submission_id": "CF263337932",
    "submission_url": "https://codeforces.com/contest/1976/submission/263337932",
    "tags": [
      "binary search",
      "dp",
      "greedy",
      "implementation",
      "two pointers",
      "*1600"
    ],
    "timestamp": "May/30/2024 16:53"
  },
  "CF263363057": {
    "contest_id": 1976,
    "language": "C++17 (GCC 7-32)",
    "path": "codeforces/1976/C.cpp",
    "platform": "Codeforces",
    "problem_index": "C",
    "problem_name": "Job Interview",
    "problem_url": "https://codeforces.com/contest/1976/problem/C",
    "submission_id": "CF263363057",
    "submission_url": "https://codeforces.com/contest/1976/submission/263363057",
    "tags": [
      "binary search",
      "dp",
      "greedy",
      "implementation",
      "two pointers",
      "*1600"
    ],
    "timestamp": "May/30/2024 17:49"
  },
  "CF263445990": {
    "contest_id": 1981,
    "language": "C++17 (GCC 7-32)",
    "path": "codeforces/1981/A.cpp",
    "platform": "Codeforces",
    "problem_index": "A",
    "problem_name": "Turtle and Piggy Are Playing a Game",
    "problem_url": "https://codeforces.com/contest/1981/problem/A",
    "submission_id": "CF263445990",
    "submission_url": "https://codeforces.com/contest/1981/submission/263445990",
    "tags": [
      "brute force",
      "greedy",
      "math",
      "*800"
    ],
    "timestamp": "May/31/2024 11:07"
  },
  "CF263451542": {
    "contest_id": 1981,
    "language": "C++17 (GCC 7-32)",
    "path": "codeforces/1981/B.cpp",
    "platform": "Codeforces",
    "problem_index": "B",
    "problem_name": "Turtle and an Infinite Sequence",
    "problem_url": "https://codeforces.com/contest/1981/problem/B",
    "submission_id": "CF263451542",
    "submission_url": "https://codeforces.com/contest/1981/submission/263451542",
    "tags": [
      "bitmasks",
      "math",
      "*1300"
    ],
    "timestamp": "May/31/2024 11:13"
  },
  "CF263475514": {
    "contest_id": 1981,
    "language": "C++17 (GCC 7-32)",
    "path": "codeforces/1981/C.cpp",
    "platform": "Codeforces",
    "problem_index": "C",
    "problem_name": "Turtle and an Incomplete Sequence",
    "problem_url": "https://codeforces.com/contest/1981/problem/C",
    "submission_id": "CF263475514",
    "submission_url": "https://codeforces.com/contest/1981/submission/263475514",
    "tags": [
      "bitmasks",
      "brute force",
      "constructive algorithms",
      "greedy",
      "implementation",
      "math",
      "*1800"
    ],
    "timestamp": "May/31/2024 12:11"
  },
  "CF264873481": {
    "contest_id": 1984,
    "language": "C++17 (GCC 7-32)",
    "path": "codeforces/1984/A.cpp",
    "platform": "Codeforces",
    "problem_index": "A",
    "problem_name": "Strange Splitting",
    "problem_url": "https://codeforces.com/contest/1984/problem/A",
    "submission_id": "CF264873481",
    "submission_url": "https://codeforces.com/contest/1984/submission/264873481",
    "tags": [
      "constructive algorithms",
      "*800"
    ],
    "timestamp": "Jun/09/2024 15:44"
  },
  "CF264884584": {
    "contest_id": 1984,
    "language": "C++17 (GCC 7-32)",
    "path": "codeforces/1984/B.cpp",
    "platform": "Codeforces",
    "problem_index": "B",
    "problem_name": "Large Addition",
    "problem_url": "https://codeforces.com/contest/1984/problem/B",
    "submission_id": "CF264884584",
    "submission_url": "https://codeforces.com/contest/1984/submission/264884584",
    "tags": [
      "implementation",
      "math",
      "*1100"
    ],
    "timestamp": "Jun/09/2024 15:54"
  },
  "CF264890502": {
    "contest_id": 1984,
    "language": "C++17 (GCC 7-32)",
    "path": "codeforces/1984/C1.cpp",
    "platform": "Codeforces",
    "problem_index": "C1",
    "problem_name": "Magnitude (Easy Version)",
    "problem_url": "https://codeforces.com/contest/1984/problem/C1",
    "submission_id": "CF264890502",
    "submission_url": "https://codeforces.com/contest/1984/submission/264890502",
    "tags": [
      "dp",
      "greedy",
      "math",
      "*1300"
    ],
    "timestamp": "Jun/09/2024 16:00"
  },
  "CF264907003": {
    "contest_id": 1984,
    "language": "C++17 (GCC 7-32)",
    "path": "codeforces/1984/C2.cpp",
    "platform": "Codeforces",
    "problem_index": "C2",
    "problem_name": "Magnitude (Hard Version)",
    "problem_url": "https://codeforces.com/contest/1984/problem/C2",
    "submission_id": "CF264907003",
    "submission_url": "https://codeforces.com/contest/1984/submission/264907003",
    "tags": [
      "combinatorics",
      "dp",
      "greedy",
      "math",
      "*1700"
    ],
    "timestamp": "Jun/09/2024 16:21"
  },
  "CF264951634": {
    "contest_id": 1984,
    "language": "C++17 (GCC 7-32)",
    "path": "codeforces/1984/D.cpp",
    "platform": "Codeforces",
    "problem_index": "D",
    "problem_name": "''a'' String Problem",
    "problem_url": "https://codeforces.com/contest/1984/problem/D",
    "submission_id": "CF264951634",
    "submission_url": "https://codeforces.com/contest/1984/submission/264951634",
    "tags": [
      "brute force",
      "hashing",
      "implementation",
      "math",
      "string suffix structures",
      "strings",
      "*2000"
    ],
    "timestamp": "Jun/09/2024 17:58"
  },
  "CF265410154": {
    "contest_id": 250,
    "language": "C++17 (GCC 7-32)",
    "path": "codeforces/250/C.cpp",
    "platform": "Codeforces",
    "problem_index": "C",
    "problem_name": "Movie Critics",
    "problem_url": "https://codeforces.com/contest/250/problem/C",
    "submission_id": "CF265410154",
    "submission_url": "https://codeforces.com/contest/250/submission/265410154",
    "tags": [
      "greedy",
      "*1600"
    ],
    "timestamp": "Jun/11/2024 21:41"
  },
  "CF269225030": {
    "contest_id": 1983,
    "language": "C++17 (GCC 7-32)",
    "path": "codeforces/1983/A.cpp",
    "platform": "Codeforces",
    "problem_index": "A",
    "problem_name": "Array Divisibility",
    "problem_url": "https://codeforces.com/contest/1983/problem/A",
    "submission_id": "CF269225030",
    "submission_url": "https://codeforces.com/contest/1983/submission/269225030",
    "tags": [
      "constructive algorithms",
      "math"
    ],
    "timestamp": "Jul/07/2024 15:37"
  },
  "CF269236815": {
    "contest_id": 1983,
    "language": "C++17 (GCC 7-32)",
    "path": "codeforces/1983/B.cpp",
    "platform": "Codeforces",
    "problem_index": "B",
    "problem_name": "Corner Twist",
    "problem_url": "https://codeforces.com/contest/1983/problem/B",
    "submission_id": "CF269236815",
    "submission_url": "https://codeforces.com/contest/1983/submission/269236815",
    "tags": [
      "constructive algorithms",
      "greedy",
      "implementation",
      "math"
    ],
    "timestamp": "Jul/07/2024 15:46"
  },
  "CF269254833": {
    "contest_id": 1983,
    "language": "C++17 (GCC 7-32)",
    "path": "codeforces/1983/C.cpp",
    "platform": "Codeforces",
    "problem_index": "C",
    "problem_name": "Have Your Cake and Eat It Too",
    "problem_url": "https://codeforces.com/contest/1983/problem/C",
    "submission_id": "CF269254833",
    "submission_url": "https://codeforces.com/contest/1983/submission/269254833",
    "tags": [
      "bitmasks",
      "dp",
      "greedy",
      "implementation"
    ],
    "timestamp": "Jul/07/2024 16:17"
  }
}